{
  "__type": "orders",
  "company_id": "TMS",
  "allow_relay": true,
  "collection_method": "P",
  "commodity": "DRY",
  "commodity_id": "DRY",
  "status": "A",
  "operational_status": "CLIN",
  "order_mode": "T",
  "ordered_method": "M",
  "bill_distance_um": "MI",
  "freight_charge_c": "USD",
  "total_charge_c": "USD",
  "otherchargetotal_c": "USD",
  "totalcharge_and_excisetax_c": "USD",
  "blnum": "1931823",
  "customer_id": "CL",
  "equipment_type_id": "V",
  "freight_charge": 2730.0,
  "freight_charge_n": 2730.0,
  "freight_charge_r": 1,
  "rate": 2730.0,
  "rate_type": "F",
  "rate_units": 1,
  "otherchargetotal": 0,
  "otherchargetotal_n": 0,
  "otherchargetotal_r": 1,
  "total_charge": 2730.0,
  "total_charge_n": 2730.0,
  "total_charge_r": 1,
  "totalcharge_and_excisetax": 2730.0,
  "totalcharge_and_excisetax_n": 2730.0,
  "totalcharge_and_excisetax_r": 1,
  "ordered_date": "20250410120550-0700",
  "shipper_stop_id": "zze59a28d262a548d9ifgAPP2",
  "consignee_stop_id": "zz1361c799f9fb4b59ifgAPP2",
  "stops": [
    {
      "__type": "stop",
      "company_id": "TMS",
      "id": "zze59a28d262a548d9ifgAPP2",
      "address": "Oakland",
      "city_name": "",
      "state": "CA",
      "zip_code": "94603",
      "location_name": null,
      "stop_type": "PU",
      "driver_load_unload": "N",
      "status": "A",
      "order_id": "1931823",
      "order_sequence": 1,
      "movement_sequence": 1,
      "sched_arrive_early": "20250123080000-0700",
      "sched_arrive_late": "20250123170000-0700"
    },
    {
      "__type": "stop",
      "company_id": "TMS",
      "id": "zzb664a912ed0f45c1ifgAPP2",
      "address": "San Jose",
      "city_name": "",
      "state": "CA",
      "zip_code": "95136",
      "location_name": null,
      "stop_type": "PU",
      "driver_load_unload": "N",
      "status": "A",
      "order_id": "1931823",
      "order_sequence": 2,
      "movement_sequence": 2,
      "sched_arrive_early": "20250123080000-0700",
      "sched_arrive_late": "20250123170000-0700"
    },
    {
      "__type": "stop",
      "company_id": "TMS",
      "id": "zzef18b14fa9f945c9ifgAPP2",
      "address": "Los Angeles",
      "city_name": "",
      "state": "CA",
      "zip_code": "90001",
      "location_name": null,
      "stop_type": "PU",
      "driver_load_unload": "N",
      "status": "A",
      "order_id": "1931823",
      "order_sequence": 3,
      "movement_sequence": 3,
      "sched_arrive_early": "20250124080000-0700",
      "sched_arrive_late": "20250124170000-0700"
    },
    {
      "__type": "stop",
      "company_id": "TMS",
      "id": "zzefc45c16f1584987ifgAPP2",
      "address": "Anaheim",
      "city_name": "",
      "state": "CA",
      "zip_code": "92806",
      "location_name": null,
      "stop_type": "PU",
      "driver_load_unload": "N",
      "status": "A",
      "order_id": "1931823",
      "order_sequence": 4,
      "movement_sequence": 4,
      "sched_arrive_early": "20250124083000-0700",
      "sched_arrive_late": "20250124173000-0700"
    },
    {
      "__type": "stop",
      "company_id": "TMS",
      "id": "zzc5cc9280f6e744b9ifgAPP2",
      "address": "Draper",
      "city_name": "",
      "state": "UT",
      "zip_code": "84020",
      "location_name": null,
      "stop_type": "SO",
      "driver_load_unload": "N",
      "status": "A",
      "order_id": "1931823",
      "order_sequence": 5,
      "movement_sequence": 5,
      "sched_arrive_early": "20250127080000-0700",
      "sched_arrive_late": "20250127103000-0700"
    },
    {
      "__type": "stop",
      "company_id": "TMS",
      "id": "zz1361c799f9fb4b59ifgAPP2",
      "address": "Draper",
      "city_name": "",
      "state": "UT",
      "zip_code": "84020",
      "location_name": null,
      "stop_type": "SO",
      "driver_load_unload": "N",
      "status": "A",
      "order_id": "1931823",
      "order_sequence": 6,
      "movement_sequence": 6,
      "sched_arrive_early": "20250127090000-0700",
      "sched_arrive_late": "20250127120000-0700"
    }
  ],
  "bill_distance": 500,
  "movement": [
    {
      "__type": "movement",
      "company_id": "TMS",
      "id": "2931823",
      "origin_stop_id": "zze59a28d262a548d9ifgAPP2",
      "dest_stop_id": "zz1361c799f9fb4b59ifgAPP2",
      "loaded": "L",
      "movement_type": "TKLD",
      "status": "A",
      "move_distance": 500,
      "move_distance_um": "MI",
      "authorized": true,
      "order_id": "1931823"
    }
  ],
  "curr_movement_id": "2931823"
}