{
  "__type": "orders",
  "company_id": "TMS",
  "allow_relay": true,
  "collection_method": "P",
  "commodity": "DRY",
  "commodity_id": "DRY",
  "status": "A",
  "operational_status": "CLIN",
  "order_mode": "T",
  "ordered_method": "M",
  "bill_distance_um": "MI",
  "freight_charge_c": "USD",
  "total_charge_c": "USD",
  "otherchargetotal_c": "USD",
  "totalcharge_and_excisetax_c": "USD",
  "blnum": "61174109",
  "customer_id": "EG",
  "equipment_type_id": "R",
  "freight_charge": 1800.0,
  "freight_charge_n": 1800.0,
  "freight_charge_r": 1,
  "rate": 1800.0,
  "rate_type": "F",
  "rate_units": 1,
  "otherchargetotal": 0,
  "otherchargetotal_n": 0,
  "otherchargetotal_r": 1,
  "total_charge": 1800.0,
  "total_charge_n": 1800.0,
  "total_charge_r": 1,
  "totalcharge_and_excisetax": 1800.0,
  "totalcharge_and_excisetax_n": 1800.0,
  "totalcharge_and_excisetax_r": 1,
  "temperature_min": 50.0,
  "temperature_max": 50.0,
  "setpoint_temp": 50.0,
  "ordered_date": "20250410120550-0700",
  "shipper_stop_id": "zz62e9a55d6d92400bifgAPP2",
  "consignee_stop_id": "zzcd8ca0163fa44941ifgAPP2",
  "stops": [
    {
      "__type": "stop",
      "company_id": "TMS",
      "id": "zz62e9a55d6d92400bifgAPP2",
      "address": "23028 RUSSELL ROAD",
      "city_name": "",
      "state": "WA",
      "zip_code": "23028",
      "location_name": "TALKINGRAIN - KENT DC",
      "stop_type": "PU",
      "driver_load_unload": "N",
      "status": "A",
      "order_id": "61174109",
      "order_sequence": 1,
      "movement_sequence": 1,
      "sched_arrive_early": "20250122120000-0700",
      "sched_arrive_late": "20250122120000-0700",
      "referenceNumbers": [
        {
          "__type": "reference_number",
          "company_id": "TMS",
          "reference_number": "TRS-0480175",
          "reference_qual": "POL",
          "send_to_driver": true,
          "stop_id": "zz62e9a55d6d92400bifgAPP2"
        }
      ]
    },
    {
      "__type": "stop",
      "company_id": "TMS",
      "id": "zzcd8ca0163fa44941ifgAPP2",
      "address": "5995 W 300 S",
      "city_name": "",
      "state": "UT",
      "zip_code": "84104",
      "location_name": "COSTCO SALT LAKE CITY #584",
      "stop_type": "SO",
      "driver_load_unload": "N",
      "status": "A",
      "order_id": "61174109",
      "order_sequence": 2,
      "movement_sequence": 2,
      "sched_arrive_early": "20250124101500-0700",
      "sched_arrive_late": "20250124101500-0700",
      "referenceNumbers": [
        {
          "__type": "reference_number",
          "company_id": "TMS",
          "reference_number": "See Notes, 005840110227",
          "reference_qual": "ON",
          "send_to_driver": true,
          "stop_id": "zzcd8ca0163fa44941ifgAPP2"
        }
      ]
    }
  ],
  "bill_distance": 100,
  "movement": [
    {
      "__type": "movement",
      "company_id": "TMS",
      "id": "62174109",
      "origin_stop_id": "zz62e9a55d6d92400bifgAPP2",
      "dest_stop_id": "zzcd8ca0163fa44941ifgAPP2",
      "loaded": "L",
      "movement_type": "TKLD",
      "status": "A",
      "move_distance": 100,
      "move_distance_um": "MI",
      "authorized": true,
      "order_id": "61174109"
    }
  ],
  "curr_movement_id": "62174109"
}