{
  "equipment_type": "Van",
  "reference_number": "6637008",
  "booking_confirmation_number": "6637008",
  "total_rate": 1300.0,
  "freight_rate": 1300.0,
  "additional_rate": 0,
  "shipper_section": [
    {
      "ship_from_company": "CARDINAL FG",
      "ship_from_address": "545 AVERY RD W, Winlock, WA 98596-9657",
      "pickup_number": null,
      "pickup_instructions": "FCFS APPOINTMENT.",
      "pickup_appointment_start_datetime": "03/04/25 06:00",
      "pickup_appointment_end_datetime": "03/04/25 20:00"
    }
  ],
  "receiver_section": [
    {
      "receiver_company": "Cascade Windows",
      "receiver_address": "5323 Harold Gatty Dr, Salt Lake City, UT 84116",
      "receiver_delivery_number": "0204618",
      "receiver_instructions": "BY APPOINTMENT",
      "receiver_appointment_start_datetime": "03/06/25 08:00",
      "receiver_appointment_end_datetime": null
    }
  ],
  "customer_name": "DM Trans, LLC dba Arrive Logistics",
  "email_domain": "arrivelogistics.com",
  "customer_address": "7701 Metropolis Dr | Bldg 15 Austin, TX 78744",
  "temperature_present": false,
  "temperature_low": null,
  "temperature_high": null,
  "is_flat_rate": true,
  "additional_rates": []
}